MANIFEST.in
README
setup.py
django_object_permissions.egg-info/PKG-INFO
django_object_permissions.egg-info/SOURCES.txt
django_object_permissions.egg-info/dependency_links.txt
django_object_permissions.egg-info/top_level.txt
object_permissions/__init__.py
object_permissions/backend.py
object_permissions/models.py
object_permissions/registration.py
object_permissions/signals.py
object_permissions/urls.py
object_permissions/migrations/0001_version_1_3.py
object_permissions/migrations/0002_version_1_4.py
object_permissions/migrations/0003_version_1_4_convert_perm_tables.py
object_permissions/migrations/0004_version_1_4_delete_old_perm_columns.py
object_permissions/migrations/__init__.py
object_permissions/muddle/__init__.py
object_permissions/muddle/mixers.py
object_permissions/static/images/shadow.png
object_permissions/static/images/icons/add.png
object_permissions/static/images/icons/delete.png
object_permissions/static/images/icons/group.png
object_permissions/static/images/icons/user.png
object_permissions/static/js/ajax_user_search.js
object_permissions/static/js/autocomplete_user_search.js
object_permissions/static/js/groups.js
object_permissions/static/js/jquery.ajax.delete.js
object_permissions/static/js/jquery.form.js
object_permissions/static/js/jquery.js
object_permissions/static/js/jquery.qtip.js
object_permissions/static/js/objects.js
object_permissions/static/js/users.js
object_permissions/templates/object_permissions/muddle/group_permissions.html
object_permissions/templates/object_permissions/muddle/user_permissions.html
object_permissions/templates/object_permissions/muddle/group/group_headers.html
object_permissions/templates/object_permissions/muddle/group/group_row.html
object_permissions/templates/object_permissions/muddle/group/user_headers.html
object_permissions/templates/object_permissions/muddle/group/user_row.html
object_permissions/templates/object_permissions/permissions/form.html
object_permissions/templates/object_permissions/permissions/group_row.html
object_permissions/templates/object_permissions/permissions/object_row.html
object_permissions/templates/object_permissions/permissions/objects.html
