Metadata-Version: 1.1
Name: django-object-permissions
Version: 1.4.6
Summary: A method for adding object-level or row-level permissions
Home-page: http://code.osuosl.org/projects/object-permissions
Author: Ken Lett
Author-email: kennric@osuosl.org
License: UNKNOWN
Platform: UNKNOWN
Classifier: License :: OSI Approved :: MIT License
Classifier: Framework :: Django
Classifier: Topic :: Security
